jeeves_core/__init__.py
jeeves_core/cli.py
jeeves_core/discover.py
jeeves_core/entry_points.py
jeeves_core/py.typed
jeeves_core-1.0.5.dist-info/entry_points.txt
jeeves_core-1.0.5.dist-info/LICENSE
jeeves_core-1.0.5.dist-info/WHEEL
jeeves_core-1.0.5.dist-info/METADATA
jeeves_core-1.0.5.dist-info/RECORD
