Metadata-Version: 2.1
Name: jeeves-core
Version: 1.0.5
Summary: Pythonic replacement for GNU Make: core
Home-page: https://github.com/jeeves-sh/jeeves-core
License: MIT
Requires-Python: >=3.8,<4.0
Classifier: Development Status :: 3 - Alpha
Classifier: Intended Audience :: Developers
Classifier: License :: OSI Approved :: MIT License
Classifier: Operating System :: OS Independent
Classifier: Programming Language :: Python :: 3
Classifier: Programming Language :: Python :: 3.10
Classifier: Programming Language :: Python :: 3.8
Classifier: Programming Language :: Python :: 3.9
Classifier: Topic :: Software Development :: Libraries :: Python Modules
Requires-Dist: boltons (>=21.0.0,<22.0.0)
Requires-Dist: documented (>=0.1.1,<0.2.0)
Requires-Dist: flake8 (<4.0.0)
Requires-Dist: more-itertools (>=9.0.0,<10.0.0)
Requires-Dist: python-benedict (>=0.24.3,<0.25.0)
Requires-Dist: typer (>=0.7.0,<0.8.0)
Project-URL: Repository, https://github.com/jeeves-sh/jeeves-core
